{"cameraMode":{"drawMode":0,"name":"Shaded","section":"Shading Mode"},"sceneLighting":true,"audioPlay":false,"sceneViewState":{"showFog":true,"showMaterialUpdate":false,"showSkybox":true,"showFlares":true,"showImageEffects":true,"showParticleSystems":true},"in2DMode":false,"pivot":{"x":-7.336645126342773,"y":-2.4896059036254885,"z":21.888534545898439},"rotation":{"x":0.2530859708786011,"y":-0.22669050097465516,"z":0.0611303374171257,"w":0.9385212063789368},"size":28.58523178100586,"orthographic":false}